cmdata/__init__.py
cmdata/common.py
cmdata/commodities/__init__.py
cmdata/commodities/point_in_time.py
cmdata-1.0.0.dist-info/LICENSE
cmdata-1.0.0.dist-info/METADATA
cmdata-1.0.0.dist-info/WHEEL
cmdata-1.0.0.dist-info/top_level.txt
cmdata-1.0.0.dist-info/RECORD
