Metadata-Version: 2.1
Name: cmdata
Version: 1.0.0
Summary: A package to process datasets provided by CargoMetrics Technologies Inc.
Author-email: "CargoMetrics Technologies Inc." <support@cargometrics.com>
License: MIT License
Project-URL: Homepage, https://github.com/cargometrics/cmdata
Project-URL: Issues, https://github.com/cargometrics/cmdata/issues
Keywords: cmdata,cargometrics,point in time
Classifier: Development Status :: 3 - Alpha
Classifier: Intended Audience :: Science/Research
Classifier: License :: OSI Approved :: MIT License
Classifier: Programming Language :: Python :: 3
Classifier: Operating System :: OS Independent
Classifier: Topic :: Scientific/Engineering
Requires-Python: >=3.9
License-File: LICENSE
Requires-Dist: pandas >1.0
Provides-Extra: all
Requires-Dist: pandas >1.0 ; extra == 'all'
Requires-Dist: pytest >=7 ; extra == 'all'
Requires-Dist: tox >4 ; extra == 'all'
Requires-Dist: twine >4 ; extra == 'all'
Provides-Extra: build
Requires-Dist: twine >4 ; extra == 'build'
Provides-Extra: test
Requires-Dist: pytest >=7 ; extra == 'test'
Requires-Dist: tox >=4 ; extra == 'test'
